{"type": "FeatureCollection", "features": [{"type": "Feature", "properties": {"name": "BFL/001", "site-address": "Molson Coors Brewery", "deliverable": "yes", "end-date": null, "entry-date": "2019-04-08", "hazardous-substances": null, "hectares": 5.1, "maximum-net-dwellings": 200.0, "minimum-net-dwellings": 140.0, "notes": "Policy SA18 in draft Local Plan (2019). Former Brewery", "organisation": "local-authority-eng:EHA", "ownership-status": "not owned by a public authority", "planning-permission-date": null, "planning-permission-history": "https://planningpublicaccess.easthants.gov.uk/online-applications/simpleSearchResults.do?action=firstPage", "planning-permission-status": "Not permissioned", "planning-permission-type": null, "point": "POINT(-0.973751 51.149028)", "site": "BFL/001", "site-plan-url": null, "start-date": "2019-04-08", "slug": "/brownfield-land/local-authority-eng/EHA/BFL-001"}, "geometry": {"type": "Point", "coordinates": [-0.973751, 51.149028]}}, {"type": "Feature", "properties": {"name": "BFL/002", "site-address": "Keydell Nurseries, Havant Road, Horndean", "deliverable": null, "end-date": null, "entry-date": "2017-05-01", "hazardous-substances": null, "hectares": 7.46, "maximum-net-dwellings": 135.0, "minimum-net-dwellings": 68.0, "notes": null, "organisation": "local-authority-eng:EHA", "ownership-status": "not owned by a public authority", "planning-permission-date": null, "planning-permission-history": "https://planningpublicaccess.easthants.gov.uk/online-applications/propertyDetails.do?activeTab=relatedCases&keyVal=_EHANT_PROPLPI_13667_2", "planning-permission-status": "Not Permissioned", "planning-permission-type": null, "point": "POINT(-0.99614 50.909805)", "site": "BFL/002", "site-plan-url": null, "start-date": "2017-05-01", "slug": "/brownfield-land/local-authority-eng/EHA/BFL-002"}, "geometry": {"type": "Point", "coordinates": [-0.99614, 50.909805]}}, {"type": "Feature", "properties": {"name": "BFL/003", "site-address": "Land rear of 8-10 London Road, Liphook", "deliverable": null, "end-date": null, "entry-date": "2017-05-01", "hazardous-substances": null, "hectares": 0.37, "maximum-net-dwellings": 11.0, "minimum-net-dwellings": 5.0, "notes": null, "organisation": "local-authority-eng:EHA", "ownership-status": "not owned by a public authority", "planning-permission-date": null, "planning-permission-history": "https://planningpublicaccess.easthants.gov.uk/online-applications/propertyDetails.do?activeTab=relatedCases&keyVal=_EHANT_PROPLPI_87185_1", "planning-permission-status": "Not Permissioned", "planning-permission-type": null, "point": "POINT(-0.801819 51.77664)", "site": "BFL/003", "site-plan-url": null, "start-date": "2017-05-01", "slug": "/brownfield-land/local-authority-eng/EHA/BFL-003"}, "geometry": {"type": "Point", "coordinates": [-0.801819, 51.77664]}}]}