{"type": "FeatureCollection", "features": [{"type": "Feature", "geometry": {"type": "Point", "coordinates": [-0.96696, 51.15936]}, "properties": {"resource-date": "2018-05-22", "entry-date": "2017-05-01", "organisation": "local-authority-eng:EHA", "site": "BFL/001", "site-address": "Convent School, Anstey Lane, Alton, GU34 2NG", "site-plan-url": null, "deliverable": null, "ownership": "not owned by a public authority", "planning-permission-status": "not permissioned", "planning-permission-type": null, "hazardous-substances": null, "latitude": 51.15936, "longitude": -0.96696, "hectares": 0.41, "minimum-net-dwellings": 6.0, "maximum-net-dwellings": 12.0, "start-date": "2017-05-01", "end-date": null, "notes": null, "resource": "2a57acb3e6ea757230b86e9092df3552024a511a99a05ed46fed48c52afe3a90"}}, {"type": "Feature", "geometry": {"type": "Point", "coordinates": [-0.99614, 50.909805]}, "properties": {"resource-date": "2018-05-22", "entry-date": "2017-05-01", "organisation": "local-authority-eng:EHA", "site": "BFL/002", "site-address": "Keydell Nurseries, Havant Road, Horndean", "site-plan-url": null, "deliverable": null, "ownership": "not owned by a public authority", "planning-permission-status": "not permissioned", "planning-permission-type": null, "hazardous-substances": null, "latitude": 50.909805, "longitude": -0.99614, "hectares": 7.46, "minimum-net-dwellings": 68.0, "maximum-net-dwellings": 135.0, "start-date": "2017-05-01", "end-date": null, "notes": null, "resource": "2a57acb3e6ea757230b86e9092df3552024a511a99a05ed46fed48c52afe3a90"}}, {"type": "Feature", "geometry": {"type": "Point", "coordinates": [-0.801819, 51.77664]}, "properties": {"resource-date": "2018-05-22", "entry-date": "2017-05-01", "organisation": "local-authority-eng:EHA", "site": "BFL/003", "site-address": "Land rear of 8-10 London Road, Liphook", "site-plan-url": null, "deliverable": null, "ownership": "not owned by a public authority", "planning-permission-status": "not permissioned", "planning-permission-type": null, "hazardous-substances": null, "latitude": 51.77664, "longitude": -0.801819, "hectares": 0.37, "minimum-net-dwellings": 5.0, "maximum-net-dwellings": 11.0, "start-date": "2017-05-01", "end-date": null, "notes": null, "resource": "2a57acb3e6ea757230b86e9092df3552024a511a99a05ed46fed48c52afe3a90"}}]}