{"type": "FeatureCollection", "features": [{"type": "Feature", "properties": {"resource": "34377bd3867f434e9e94176a0fdf8a10905bb87eb3bfbdde762eed1f3b5c7555", "site-address": "Molson Coors Brewery", "deliverable": "yes", "end-date": null, "entry-date": "2019-04-08", "hazardous-substances": null, "hectares": "5.1", "maximum-net-dwellings": 200.0, "minimum-net-dwellings": 140.0, "notes": "Policy SA18 in draft Local Plan (2019). Former Brewery", "organisation": "local-authority-eng:EHA", "ownership-status": "not owned by a public authority", "planning-permission-date": null, "planning-permission-history": "https://planningpublicaccess.easthants.gov.uk/online-applications/simpleSearchResults.do?action=firstPage", "planning-permission-status": "Not permissioned", "planning-permission-type": null, "point": "POINT(-0.973751 51.149028)", "site": "BFL/001", "site-plan-url": null, "start-date": "2019-04-08", "slug": "brownfield-land/local-authority-eng/EHA/BFL-001"}, "geometry": {"type": "Point", "coordinates": [-0.973751, 51.149028]}}]}